tfprimate/__init__.py
tfprimate/alignment.py
tfprimate/getInfo.py
tfprimate/phyloTree.py
tfprimate/primate_rnaseq.py
tfprimate-0.1.4.dist-info/LICENSE
tfprimate-0.1.4.dist-info/METADATA
tfprimate-0.1.4.dist-info/WHEEL
tfprimate-0.1.4.dist-info/RECORD
