Metadata-Version: 2.1
Name: tfprimate
Version: 0.1.4
Summary: A package for primate transcription factors database
License: MIT
Author: Yao-Chung Chen, Ekin Deniz Aksu, Melanie Sarfert, Katja Nowick
Requires-Python: >=3.9,<4.0
Classifier: License :: OSI Approved :: MIT License
Classifier: Programming Language :: Python :: 3
Classifier: Programming Language :: Python :: 3.9
Classifier: Programming Language :: Python :: 3.10
Classifier: Programming Language :: Python :: 3.11
